as_ws_wrapper/__init__.py
as_ws_wrapper/_version.py
as_ws_wrapper/constants.py
as_ws_wrapper/response.py
as_ws_wrapper/adapters/__init__.py
as_ws_wrapper/adapters/csv.py
as_ws_wrapper/models/__init__.py
as_ws_wrapper/models/base.py
as_ws_wrapper/wrapper/__init__.py
as_ws_wrapper/wrapper/as_ws.py
as_ws_wrapper/wrapper/soap.py
as_ws_wrapper-0.0.10.dist-info/METADATA
as_ws_wrapper-0.0.10.dist-info/WHEEL
as_ws_wrapper-0.0.10.dist-info/top_level.txt
as_ws_wrapper-0.0.10.dist-info/RECORD
