Metadata-Version: 2.1
Name: as-ws-wrapper
Version: 0.0.10
Summary: Cliente não oficial do webservice Accesstage
Home-page: https://github.com/imobanco/as-webservice-wrapper
Author: Imobanco
License: UNKNOWN
Project-URL: Source, https://github.com/imobanco/as-webservice-wrapper
Project-URL: Tracker, https://github.com/imobanco/as-webservice-wrapper/issues
Platform: UNKNOWN
Classifier: Programming Language :: Python :: 3
Classifier: Development Status :: 3 - Alpha
Classifier: Intended Audience :: Developers
Classifier: Environment :: Web Environment
Classifier: License :: OSI Approved :: GNU General Public License v3 (GPLv3)
Classifier: Natural Language :: Portuguese (Brazilian)
Classifier: Operating System :: OS Independent
Classifier: Topic :: Documentation :: Sphinx
Classifier: Topic :: Software Development :: Libraries :: Python Modules
Classifier: Topic :: Internet :: WWW/HTTP :: Dynamic Content :: CGI Tools/Libraries
Classifier: Topic :: Utilities
Classifier: 
Classifier: 
Requires-Python: >=3.8
Requires-Dist: python-decouple (>=3.3)
Requires-Dist: pydantic (>=1.7.0)
Requires-Dist: zeep (>=4.0.*)
